AUTHORS.rst
CONTRIBUTING.rst
HISTORY.rst
LICENSE
MANIFEST.in
README.rst
setup.cfg
setup.py
django_green_grove/__init__.py
django_green_grove/apps.py
django_green_grove/backends.py
django_green_grove.egg-info/PKG-INFO
django_green_grove.egg-info/SOURCES.txt
django_green_grove.egg-info/dependency_links.txt
django_green_grove.egg-info/not-zip-safe
django_green_grove.egg-info/top_level.txt
django_green_grove/management/__init__.py
django_green_grove/management/commands/__init__.py
django_green_grove/management/commands/backup_project.py