Metadata-Version: 1.1
Name: django-green-grove
Version: 0.1.2
Summary: Collection of helpers to back up Django projects that use a Postgres database and a S3 bucket as media storage.
Home-page: https://github.com/dreipol/django-green-grove
Author: dreipol GmbH
Author-email: dev@dreipol.ch
License: MIT
Keywords: django-green-grove
Platform: UNKNOWN
Classifier: Development Status :: 3 - Alpha
Classifier: Framework :: Django
Classifier: Framework :: Django :: 1.8
Classifier: Framework :: Django :: 1.9
Classifier: Framework :: Django :: 1.10
Classifier: Intended Audience :: Developers
Classifier: License :: OSI Approved :: BSD License
Classifier: Natural Language :: English
Classifier: Programming Language :: Python :: 2
Classifier: Programming Language :: Python :: 2.7
Classifier: Programming Language :: Python :: 3
Classifier: Programming Language :: Python :: 3.3
Classifier: Programming Language :: Python :: 3.4
Classifier: Programming Language :: Python :: 3.5
